htmlfn/__init__.py
htmlfn-0.0.4.dist-info/LICENSE
htmlfn-0.0.4.dist-info/METADATA
htmlfn-0.0.4.dist-info/WHEEL
htmlfn-0.0.4.dist-info/top_level.txt
htmlfn-0.0.4.dist-info/RECORD
