Metadata-Version: 2.1
Name: htmlfn
Version: 0.0.4
Summary: functions for generating html
Home-page: https://github.com/tgbugs/pyontutils/tree/master/htmlfn
Author: Tom Gillespie
Author-email: tgbugs@gmail.com
License: MIT
Keywords: html tags functional
Platform: UNKNOWN
Classifier: Development Status :: 4 - Beta
Classifier: License :: OSI Approved :: MIT License
Classifier: Programming Language :: Python :: 3.6
Classifier: Programming Language :: Python :: 3.7
Requires-Python: >=3.6
Provides-Extra: dev
Requires-Dist: pytest-cov ; extra == 'dev'
Requires-Dist: wheel ; extra == 'dev'
Provides-Extra: test
Requires-Dist: pytest ; extra == 'test'
Requires-Dist: pytest-runner ; extra == 'test'
